supportbot/__init__.py
supportbot/bots.py
supportbot/common.py
supportbot/full_text_search/__init__.py
supportbot/full_text_search/bot.py
supportbot/full_text_search/index.py
supportbot/full_text_search/search.py
supportbot/fuzzy_matching/__init__.py
supportbot/fuzzy_matching/bot.py
supportbot-0.0.2.dist-info/LICENSE
supportbot-0.0.2.dist-info/METADATA
supportbot-0.0.2.dist-info/WHEEL
supportbot-0.0.2.dist-info/top_level.txt
supportbot-0.0.2.dist-info/RECORD
