Metadata-Version: 2.1
Name: supportbot
Version: 0.0.2
Summary: Supportbot to support questions and their answers
Home-page: https://github.com/zhangkaizhao/supportbot
Author: Kaizhao Zhang
Author-email: zhangkaizhao@gmail.com
License: MIT
Platform: UNKNOWN
Classifier: Intended Audience :: Developers
Classifier: License :: OSI Approved :: MIT License
Classifier: Operating System :: OS Independent
Classifier: Programming Language :: Python
Classifier: Programming Language :: Python :: 3
Classifier: Programming Language :: Python :: 3.6
Classifier: Programming Language :: Python :: 3.7
Requires-Python: >=3.6
Requires-Dist: fuzzywuzzy[speedup] (>=0.17.0)
Requires-Dist: jieba (>=0.39)
Requires-Dist: Whoosh (>=2.7.4)
